trafalgar.py
trafalgar.py-0.1.7.dist-info/METADATA
trafalgar.py-0.1.7.dist-info/WHEEL
trafalgar.py-0.1.7.dist-info/top_level.txt
trafalgar.py-0.1.7.dist-info/RECORD
