Metadata-Version: 2.1
Name: trafalgar.py
Version: 0.1.7
Summary: Trafalgar makes quantitative finance and portfolio analysis faster and easier
Home-page: https://github.com/ssantoshp/trafalgar
Author: Santosh Passoubady
Author-email: santoshpassoubady@gmail.com
License: MIT
Platform: UNKNOWN
Requires-Dist: numpy
Requires-Dist: matplotlib
Requires-Dist: pykalman
Requires-Dist: seaborn
Requires-Dist: scipy
Requires-Dist: pandas-datareader
Requires-Dist: datetime
Requires-Dist: statsmodels
Requires-Dist: sklearn
Requires-Dist: pyportfolioopt
